CHANGES.rst
CONTRIBUTING.rst
LICENSE
MANIFEST.in
README.rst
setup.py
extras/wifi-completion.bash
pyiw/__init__.py
pyiw/__main__.py
pyiw/cli.py
pyiw/exceptions.py
pyiw/scan.py
pyiw/scheme.py
pyiw/subprocess_compat.py
pyiw/utils.py
pyiw.egg-info/PKG-INFO
pyiw.egg-info/SOURCES.txt
pyiw.egg-info/dependency_links.txt
pyiw.egg-info/entry_points.txt
pyiw.egg-info/requires.txt
pyiw.egg-info/top_level.txt