Metadata-Version: 1.1
Name: pyiw
Version: 1.0.0
Summary: 
